meningotype/__init__.py
meningotype/check_deps.py
meningotype/ctrA.py
meningotype/finetype.py
meningotype/meningotype.py
meningotype/menwy.py
meningotype/nmen.py
meningotype/porB.py
meningotype/verification.py
meningotype/db/BASTalleles.txt
meningotype/db/BASTalleles.txt.old
meningotype/db/FetA_VR.fas
meningotype/db/FetA_VR.fas.old
meningotype/db/NHBA_peptide.fas
meningotype/db/NHBA_peptide.fas.old
meningotype/db/NadA_peptide.fas
meningotype/db/NadA_peptide.fas.old
meningotype/db/PorA.fa
meningotype/db/PorA_VR1.fas
meningotype/db/PorA_VR1.fas.old
meningotype/db/PorA_VR2.fas
meningotype/db/PorA_VR2.fas.old
meningotype/db/PorB.fas
meningotype/db/PorB.fas.old
meningotype/db/bexseroPRIMERS
meningotype/db/ctrA.fa
meningotype/db/ctrAPRIMERS
meningotype/db/fHbp_peptide.fas
meningotype/db/fHbp_peptide.fas.old
meningotype/db/finetypePRIMERS
meningotype/db/seroALLELES.fa
meningotype/db/seroPRIMERS
meningotype/db/blast/NHBA_peptide.phr
meningotype/db/blast/NHBA_peptide.pin
meningotype/db/blast/NHBA_peptide.psq
meningotype/db/blast/NadA_peptide.phr
meningotype/db/blast/NadA_peptide.pin
meningotype/db/blast/NadA_peptide.psq
meningotype/db/blast/ctrA.nhr
meningotype/db/blast/ctrA.nin
meningotype/db/blast/ctrA.nsq
meningotype/db/blast/fHbp_peptide.phr
meningotype/db/blast/fHbp_peptide.pin
meningotype/db/blast/fHbp_peptide.psq
meningotype/db/blast/fet.phr
meningotype/db/blast/fet.pin
meningotype/db/blast/fet.psq
meningotype/db/blast/porA.nhr
meningotype/db/blast/porA.nin
meningotype/db/blast/porA.nsq
meningotype/db/blast/porA1.phr
meningotype/db/blast/porA1.pin
meningotype/db/blast/porA1.psq
meningotype/db/blast/porA2.phr
meningotype/db/blast/porA2.pin
meningotype/db/blast/porA2.psq
meningotype/db/blast/porB.nhr
meningotype/db/blast/porB.nin
meningotype/db/blast/porB.nsq
meningotype/db/blast/seroALLELES.nhr
meningotype/db/blast/seroALLELES.nin
meningotype/db/blast/seroALLELES.nsq
meningotype/db/blast/synG.nhr
meningotype/db/blast/synG.nin
meningotype/db/blast/synG.nsq
meningotype-0.8.5.dist-info/LICENSE
meningotype-0.8.5.dist-info/METADATA
meningotype-0.8.5.dist-info/WHEEL
meningotype-0.8.5.dist-info/entry_points.txt
meningotype-0.8.5.dist-info/top_level.txt
meningotype-0.8.5.dist-info/RECORD
