Metadata-Version: 2.1
Name: meningotype
Version: 0.8.5
Summary: In silico serotyping and finetyping (porA and fetA) of Neisseria meningitidis
Home-page: https://github.com/MDU-PHL/meningotype
Author: Jason Kwong
Author-email: kwongj@gmail.com
License: GPLv3
Keywords: microbial genomics Neisseria sequence typing
Platform: UNKNOWN
Classifier: Development Status :: 4 - Beta
Classifier: License :: OSI Approved :: GNU General Public License v3 (GPLv3)
Classifier: Programming Language :: Python :: 3.6
Classifier: Programming Language :: Python :: 3.7
Classifier: Programming Language :: Python :: 3.8
Classifier: Programming Language :: Python :: 3.9
Classifier: Topic :: Scientific/Engineering :: Bio-Informatics
Classifier: Topic :: Scientific/Engineering :: Medical Science Apps.
Classifier: Intended Audience :: Science/Research
License-File: LICENSE
Requires-Dist: biopython
